CF/__init__.py
CF/textile.py
CF/pipeline/__init__.py
CF/pipeline/pipeline.py
CF/pipeline/steps/__init__.py
CF/pipeline/steps/filter_.py
CF/pipeline/steps/preflight.py
CF/pipeline/steps/process.py
CF/pipeline/steps/step.py
CF/pipeline/steps/transform.py
textilepy-0.1.0.dist-info/LICENSE
textilepy-0.1.0.dist-info/METADATA
textilepy-0.1.0.dist-info/WHEEL
textilepy-0.1.0.dist-info/top_level.txt
textilepy-0.1.0.dist-info/RECORD
