Metadata-Version: 2.1
Name: textilepy
Version: 0.1.0
Summary: UNKNOWN
Home-page: https://github.com/ETKiwi/
Author: Bill Kuo
Author-email: billnd12765@gmail.com
License: MIT
Platform: UNKNOWN
Classifier: License :: OSI Approved :: MIT License
Classifier: Programming Language :: Python
Classifier: Programming Language :: Python :: 3
Classifier: Programming Language :: Python :: 3.6
Classifier: Programming Language :: Python :: Implementation :: CPython
Classifier: Programming Language :: Python :: Implementation :: PyPy
Requires-Python: >=3.6.0
License-File: LICENSE
Requires-Dist: numpy
Requires-Dist: pandas
Requires-Dist: re
Requires-Dist: os
Requires-Dist: glob
